[
  {
    "inputs": [],
    "name": "getMinCollateralRatio",
    "outputs": [
      {
        "internalType": "uint256",
        "name": "",
        "type": "uint256"
      }
    ],
    "stateMutability": "view",
    "type": "function"
  },
  {
    "inputs": [
      {
        "internalType": "address",
        "name": "minter",
        "type": "address"
      },
      {
        "internalType": "uint256",
        "name": "assetPrice",
        "type": "uint256"
      }
    ],
    "name": "getMinterCollateralRatio",
    "outputs": [
      {
        "internalType": "uint256",
        "name": "",
        "type": "uint256"
      }
    ],
    "stateMutability": "view",
    "type": "function"
  },
  {
    "inputs": [],
    "name": "getNumPages",
    "outputs": [
      {
        "internalType": "uint256",
        "name": "",
        "type": "uint256"
      }
    ],
    "stateMutability": "view",
    "type": "function"
  },
  {
    "inputs": [
      {
        "internalType": "uint256",
        "name": "pageIndex",
        "type": "uint256"
      },
      {
        "internalType": "uint256",
        "name": "assetPrice",
        "type": "uint256"
      }
    ],
    "name": "getUserReserveInfo",
    "outputs": [
      {
        "internalType": "address[]",
        "name": "addresses",
        "type": "address[]"
      },
      {
        "internalType": "uint256[]",
        "name": "debts",
        "type": "uint256[]"
      },
      {
        "internalType": "uint256[]",
        "name": "collateralRatios",
        "type": "uint256[]"
      }
    ],
    "stateMutability": "view",
    "type": "function"
  }
]
